{
  "id": "cssloaders-github-27",
  "name": "CSSLoaders Pattern 27",
  "category": "pulse",
  "tags": [
    "cssloaders",
    "ring",
    "pulse",
    "loader"
  ],
  "formats": [
    "html",
    "css",
    "react"
  ],
  "flags": {
    "popular": false,
    "singleElement": true,
    "cssOnly": true,
    "tailwind": false,
    "customizable": true
  },
  "searchText": "cssloaders-github-27 cssloaders pattern 27 pulse cssloaders ring pulse loader html css react singleelement cssonly customizable",
  "previewHtml": "<span class=\"darma-loader-cssloaders-github-27\"></span>",
  "previewCss": ".darma-loader-cssloaders-github-27 {\n  display: inline-block;\n  width: 57px;\n  height: 57px;\n  border-radius: 50%;\n  border: 3px solid var(--loader-color, #0ea5e9);\n  animation: darma-loader-cssloaders-github-27-ringPulse 1.45s ease-out infinite;\n}\n@keyframes darma-loader-cssloaders-github-27-ringPulse { 0% { transform: scale(.45); opacity: 1; } 100% { transform: scale(1.15); opacity: 0; } }\n",
  "defaults": {
    "color": "#0ea5e9",
    "secondaryColor": "#bae6fd",
    "size": 58,
    "speed": 1.15
  },
  "code": {
    "html": "<span class=\"darma-loader-cssloaders-github-27\"></span>",
    "css": ".darma-loader-cssloaders-github-27 {\n  display: inline-block;\n  width: 57px;\n  height: 57px;\n  border-radius: 50%;\n  border: 3px solid var(--loader-color, #0ea5e9);\n  animation: darma-loader-cssloaders-github-27-ringPulse 1.45s ease-out infinite;\n}\n@keyframes darma-loader-cssloaders-github-27-ringPulse { 0% { transform: scale(.45); opacity: 1; } 100% { transform: scale(1.15); opacity: 0; } }\n",
    "react": "export default function CssloadersGithub27Loader() {\n  return (\n    <span className=\"darma-loader-cssloaders-github-27\"></span>\n  );\n}\n"
  },
  "controls": {
    "color": true,
    "size": true,
    "speed": true,
    "background": false,
    "secondaryColor": false
  },
  "source": {
    "name": "cssloaders.github.io",
    "author": "cssloaders",
    "license": "MIT",
    "url": "https://github.com/cssloaders/cssloaders.github.io"
  }
}
