{
  "id": "darma-custom-260",
  "name": "Wave Rail March",
  "category": "progress",
  "tags": [
    "wave",
    "rail",
    "march",
    "progress",
    "track",
    "mask",
    "loader",
    "css-only",
    "single-element",
    "batch-05"
  ],
  "html": "<div class=\"loader\"></div>",
  "css": ".loader {\n  color: var(--loader-color, #16a34a);\n  height: 30px;\n  aspect-ratio: 6;\n  --c: #0000 64%,currentColor 66% 98%,#0000 101%;\n  background:\n    radial-gradient(35% 146% at 50% 159%,var(--c)) 0 0,\n    radial-gradient(35% 146% at 50% -59%,var(--c)) 25% 100%;\n  background-size: calc(100%/3) 50%;\n  background-repeat: repeat-x;\n  animation: l1 1s infinite linear;\n}\n@keyframes l1{\n  to {background-position: 50% 0,75% 100%}\n}\n",
  "source": {
    "name": "Darma custom loaders",
    "author": "Darma",
    "license": "Custom"
  },
  "controls": {
    "color": true,
    "secondaryColor": false,
    "size": true,
    "speed": true,
    "background": false
  },
  "defaults": {
    "color": "#16a34a",
    "secondaryColor": "#86efac",
    "size": 84,
    "speed": 1.0,
    "background": "#ffffff"
  },
  "flags": {
    "popular": false,
    "singleElement": true,
    "cssOnly": true,
    "tailwind": false,
    "customizable": true
  }
}
